ms1searchpy/__init__.py
ms1searchpy/combine.py
ms1searchpy/combine_proteins.py
ms1searchpy/directms1quant.py
ms1searchpy/directms1quantmulti.py
ms1searchpy/group_specific.py
ms1searchpy/main.py
ms1searchpy/ms1todiffacto.py
ms1searchpy/search.py
ms1searchpy/utils.py
ms1searchpy/utils_figures.py
ms1searchpy-2.8.9.dist-info/LICENSE
ms1searchpy-2.8.9.dist-info/METADATA
ms1searchpy-2.8.9.dist-info/WHEEL
ms1searchpy-2.8.9.dist-info/entry_points.txt
ms1searchpy-2.8.9.dist-info/top_level.txt
ms1searchpy-2.8.9.dist-info/RECORD
