Metadata-Version: 2.1
Name: ms1searchpy
Version: 2.8.9
Summary: A proteomics search engine for LC-MS1 spectra.
Author: Mark Ivanov
Author-email: pyteomics@googlegroups.com
License: License :: OSI Approved :: Apache Software License
Classifier: Intended Audience :: Science/Research
Classifier: Programming Language :: Python :: 3
Classifier: Topic :: Education
Classifier: Topic :: Scientific/Engineering :: Bio-Informatics
Classifier: Topic :: Scientific/Engineering :: Chemistry
Classifier: Topic :: Scientific/Engineering :: Physics
License-File: LICENSE
Requires-Dist: pyteomics >=4.5.1
Requires-Dist: lxml
Requires-Dist: scipy
Requires-Dist: numpy
Requires-Dist: scikit-learn
Requires-Dist: lightgbm
Requires-Dist: pandas
Requires-Dist: biosaur2
Requires-Dist: matplotlib
Requires-Dist: seaborn
Requires-Dist: ete3
